Metadata-Version: 1.0
Name: psdPy
Version: 0.1.0
Summary: Python implementation of scPSD
Home-page: UNKNOWN
Author: Forrest Koch
Author-email: forrest.c.koch@gmail.com
License: UNKNOWN
Platform: UNKNOWN
